reading_image/Processed.py
reading_image/Session.py
reading_image/__init__.py
reading_image-1.0.1.dist-info/LICENSE
reading_image-1.0.1.dist-info/METADATA
reading_image-1.0.1.dist-info/WHEEL
reading_image-1.0.1.dist-info/top_level.txt
reading_image-1.0.1.dist-info/RECORD
