Metadata-Version: 2.1
Name: reading-image
Version: 1.0.1
Summary: Reading Image is a text analysis tool for images files (png, jpg, jpeg) and pdf. The system will preform OCR on the document and return details of the text within. Examples of analysis include text strings, page location and entity analysis. Advanced OCR will also read and understand table formats, and translation is available to English from French. 
Home-page: http://bitbucket.org/DannyHoskin/reading_image_python
Author: Danny Hoskin
Author-email: contact@nihsko.com
License: Nihsko
Keywords: ReadingImage text analysis ocr nlp pdf image extraction table entity recognition translation
Platform: UNKNOWN
Requires-Dist: pandas
